alphalogic_api/__init__.py
alphalogic_api/attributes.py
alphalogic_api/conf_inspector.py
alphalogic_api/decorators.py
alphalogic_api/exceptions.py
alphalogic_api/logger.py
alphalogic_api/manager.py
alphalogic_api/multistub.py
alphalogic_api/options.py
alphalogic_api/tasks_pool.py
alphalogic_api/utils.py
alphalogic_api/objects/__init__.py
alphalogic_api/objects/command.py
alphalogic_api/objects/event.py
alphalogic_api/objects/object.py
alphalogic_api/objects/parameter.py
alphalogic_api/protocol/__init__.py
alphalogic_api/protocol/rpc_pb2.py
alphalogic_api/protocol/rpc_pb2_grpc.py
alphalogic_api/tests/__init__.py
alphalogic_api/tests/api_test.py
alphalogic_api/tests/handlers_test.py
alphalogic_api/tests/test2.py
alphalogic_api-0.0.27.dist-info/LICENSE
alphalogic_api-0.0.27.dist-info/METADATA
alphalogic_api-0.0.27.dist-info/WHEEL
alphalogic_api-0.0.27.dist-info/top_level.txt
alphalogic_api-0.0.27.dist-info/RECORD
