Metadata-Version: 2.1
Name: alphalogic-api
Version: 0.0.27
Summary: Python stub library for Alphalogic adapters.
Home-page: https://github.com/Alphaopen/alphalogic_api
Author: Alphaopen
Author-email: mo@alphaopen.com
License: MIT
Platform: linux2
Platform: win32
Classifier: Programming Language :: Python :: 2.7
Classifier: License :: OSI Approved :: MIT License
Classifier: Operating System :: OS Independent
Requires-Dist: protobuf (==3.17.3)
Requires-Dist: grpcio (==1.39.0)
Requires-Dist: grpcio-tools (==1.39.0)
